pyrosetta_distributed/__init__.py
pyrosetta_distributed-0.0.4.dist-info/METADATA
pyrosetta_distributed-0.0.4.dist-info/WHEEL
pyrosetta_distributed-0.0.4.dist-info/top_level.txt
pyrosetta_distributed-0.0.4.dist-info/RECORD
